{
  "gt_parse": {
    "menu": [
      {
        "nm": "Pan BBQ Poncho",
        "cnt": "1",
        "price": "14,49",
		"etc":"32"
		
		
		
		
        

      }
    
    ],
    "sub_total": {
      "subtotal_price": "13,54"
      
    },
    "total": {
      "total_price": "14,49",
	  "cashprice": "14,49"
	  
	  
	  
	  
	  
	  
	  
	  
    }
  },
  "meta": {
    "version": "2.0.0",
    "split": "train",
    "image_id": 26,
    "image_size": {
      "width": 1280,
      "height": 855
    }
  },
  "valid_line": [
  ],
  "ROI":{
  }
  }